openmeter/__init__.py
openmeter/_base_client.py
openmeter/_client.py
openmeter/_compat.py
openmeter/_constants.py
openmeter/_exceptions.py
openmeter/_files.py
openmeter/_models.py
openmeter/_qs.py
openmeter/_resource.py
openmeter/_response.py
openmeter/_streaming.py
openmeter/_types.py
openmeter/_version.py
openmeter/py.typed
openmeter/_utils/__init__.py
openmeter/_utils/_logs.py
openmeter/_utils/_proxy.py
openmeter/_utils/_reflection.py
openmeter/_utils/_streams.py
openmeter/_utils/_sync.py
openmeter/_utils/_transform.py
openmeter/_utils/_typing.py
openmeter/_utils/_utils.py
openmeter/lib/.keep
openmeter/resources/__init__.py
openmeter/resources/events.py
openmeter/resources/subjects.py
openmeter/resources/debug/__init__.py
openmeter/resources/debug/debug.py
openmeter/resources/debug/metrics.py
openmeter/resources/entitlements/__init__.py
openmeter/resources/entitlements/entitlements.py
openmeter/resources/entitlements/features.py
openmeter/resources/entitlements/grants.py
openmeter/resources/meters/__init__.py
openmeter/resources/meters/meters.py
openmeter/resources/meters/subjects.py
openmeter/resources/notifications/__init__.py
openmeter/resources/notifications/channels.py
openmeter/resources/notifications/events.py
openmeter/resources/notifications/notifications.py
openmeter/resources/notifications/rules.py
openmeter/resources/notifications/webhook.py
openmeter/resources/portal/__init__.py
openmeter/resources/portal/meters.py
openmeter/resources/portal/portal.py
openmeter/resources/portal/tokens.py
openmeter/resources/subjects/entitlements/__init__.py
openmeter/resources/subjects/entitlements/entitlements.py
openmeter/resources/subjects/entitlements/grants.py
openmeter/types/__init__.py
openmeter/types/entitlement.py
openmeter/types/event_ingest_params.py
openmeter/types/event_ingest_response.py
openmeter/types/event_list_params.py
openmeter/types/event_list_response.py
openmeter/types/ingested_event.py
openmeter/types/list_entitlements_result.py
openmeter-2.0.0.dist-info/METADATA
openmeter-2.0.0.dist-info/WHEEL
openmeter-2.0.0.dist-info/licenses/LICENSE
openmeter-2.0.0.dist-info/RECORD
